confuzzle
