Metadata-Version: 1.0
Name: confuzzle
Version: 0.2.0
Summary: A tiny tool for generating templated config files
Home-page: http://github.com/j4mie/confuzzle
Author: Jamie Matthews
Author-email: jamie.matthews@gmail.com
License: Public Domain
Platform: UNKNOWN
Classifier: Programming Language :: Python
Classifier: Development Status :: 3 - Alpha
Classifier: Intended Audience :: Developers
Classifier: License :: Public Domain
